Metadata-Version: 1.1
Name: aws-ssm-invoke
Version: 1.0.0
Summary: A wrapper around an AWS SSM send-command that can optionally wait for execution success.
Home-page: https://github.com/stevemac007/aws-ssm-cli-invoke
Author: Steve Mactaggart
Author-email: steve@whitesquaresoft.com
License: MIT
Download-URL: https://github.com/stevemac007/aws-ssm-cli-invoke/archive/1.0.0.tar.gz
Keywords: aws ssm generation
Platform: UNKNOWN
Classifier: Development Status :: 3 - Alpha
Classifier: Environment :: Console
Classifier: Operating System :: POSIX :: Linux
Classifier: Intended Audience :: Developers
Classifier: Intended Audience :: System Administrators
Classifier: License :: OSI Approved :: MIT License
Classifier: Programming Language :: Python :: 2
Classifier: Programming Language :: Python :: 2.6
Classifier: Programming Language :: Python :: 2.7
Classifier: Programming Language :: Python :: 3.6
Classifier: Programming Language :: Python :: 3.7
